py_data_viewer/__init__.py
py_data_viewer/file_output.py
py_data_viewer/py_data_viewer.py
py_data_viewer/types.py
py_data_viewer-0.0.9.dist-info/LICENSE
py_data_viewer-0.0.9.dist-info/METADATA
py_data_viewer-0.0.9.dist-info/WHEEL
py_data_viewer-0.0.9.dist-info/RECORD
