Metadata-Version: 2.3
Name: py-data-viewer
Version: 0.0.9
Summary: A python library to display data structure values for easier navigation and exploration.
License: MIT
Keywords: python,data,viewer,debugging,exploration
Author: Matt Lucero
Author-email: matt_lucero@outlook.com
Requires-Python: >=3.8,<4.0
Classifier: Intended Audience :: Developers
Classifier: License :: OSI Approved :: MIT License
Classifier: Operating System :: OS Independent
Classifier: Programming Language :: Python :: 3
Classifier: Programming Language :: Python :: 3.8
Classifier: Programming Language :: Python :: 3.9
Classifier: Programming Language :: Python :: 3.10
Classifier: Programming Language :: Python :: 3.11
Classifier: Programming Language :: Python :: 3.12
Classifier: Programming Language :: Python :: 3.13
Classifier: Topic :: Software Development :: Debuggers
Classifier: Topic :: Software Development :: Libraries :: Python Modules
Classifier: Topic :: Utilities
Project-URL: Homepage, https://github.com/Attention-Mechanism/py-data-viewer
Project-URL: Repository, https://github.com/Attention-Mechanism/py-data-viewer
